LICENSE
MANIFEST.in
README.md
setup.py
unisense_xlink/__init__.py
unisense_xlink/core.py
unisense_xlink/models.py
unisense_xlink/sensors.py
unisense_xlink.egg-info/PKG-INFO
unisense_xlink.egg-info/SOURCES.txt
unisense_xlink.egg-info/dependency_links.txt
unisense_xlink.egg-info/not-zip-safe
unisense_xlink.egg-info/requires.txt
unisense_xlink.egg-info/top_level.txt